pyserv
